rocket/__init__.py
rocket/rocket.py
rocket_1.1.1-1.0.0.dist-info/LICENSE.txt
rocket_1.1.1-1.0.0.dist-info/METADATA
rocket_1.1.1-1.0.0.dist-info/WHEEL
rocket_1.1.1-1.0.0.dist-info/top_level.txt
rocket_1.1.1-1.0.0.dist-info/RECORD
