Metadata-Version: 2.1
Name: rocket-1.1.1
Version: 1.0.0
Summary: An awesome package that does something
Home-page: http://pypi.python.org/pypi/rocket/
Author: ha115
Author-email: h.benghenima@esi-sba.dz
License: LICENSE.txt
License-File: LICENSE.txt
Requires-Dist: rocket
